sprockets.mixins.cors-0.1.1-py3.4-nspkg.pth
sprockets/mixins/cors.py
sprockets.mixins.cors-0.1.1.dist-info/zip-safe
sprockets.mixins.cors-0.1.1.dist-info/namespace_packages.txt
sprockets.mixins.cors-0.1.1.dist-info/top_level.txt
sprockets.mixins.cors-0.1.1.dist-info/METADATA
sprockets.mixins.cors-0.1.1.dist-info/DESCRIPTION.rst
sprockets.mixins.cors-0.1.1.dist-info/metadata.json
sprockets.mixins.cors-0.1.1.dist-info/WHEEL
sprockets.mixins.cors-0.1.1.dist-info/RECORD
