Metadata-Version: 2.0
Name: sprockets.mixins.cors
Version: 0.1.1
Summary: Tornado RequestHandler mix-in for implementing a CORS enabled endpoint.
Home-page: https://github.com/sprockets/sprockets.mixins.cors.git
Author: AWeber Communications, Inc.
Author-email: api@aweber.com
License: BSD
Platform: UNKNOWN
Classifier: Development Status :: 4 - Beta
Classifier: Intended Audience :: Developers
Classifier: License :: OSI Approved :: BSD License
Classifier: Natural Language :: English
Classifier: Operating System :: OS Independent
Classifier: Programming Language :: Python :: 2
Classifier: Programming Language :: Python :: 2.7
Classifier: Programming Language :: Python :: 3
Classifier: Programming Language :: Python :: 3.4
Classifier: Programming Language :: Python :: Implementation :: CPython
Requires-Dist: tornado (>=3.1,<5)
